{
    "$schema": "http://json-schema.org/draft-07/schema#",
    "$id": "ServiceOrderItem.schema.json",
    "title": "ServiceOrderItem",
    "type": "object",
    "properties": {
        "action": {
            "type": "string"
        },
        "id": {
            "type": "string"
        },
        "state": {
            "type": "string"
        },
        "service": {
            "$ref": "Service.schema.json/#definitions/Service"
        },
        "orderItemRelationship": {
            "type": "array",
            "items": {
                "$ref": "../Customer/OrderItemRelationship.schema.json/#definitions/OrderItemRelationship"
            }
        },
        "appointment": {
            "type": "array",
            "items": {
                "$ref": "../Customer/AppointmentRef.schema.json/#definitions/AppointmentRef"
            }
        }
    },
    "allOf": [
        {
            "$ref": "../Common/CommonComponents.schema.json/#polymorphicPattern"
        }
    ]
}
